uipath_llm_client/__init__.py
uipath_llm_client/__version__.py
uipath_llm_client/httpx_client.py
uipath_llm_client/clients/anthropic/__init__.py
uipath_llm_client/clients/anthropic/client.py
uipath_llm_client/clients/google/__init__.py
uipath_llm_client/clients/google/client.py
uipath_llm_client/clients/openai/__init__.py
uipath_llm_client/clients/openai/client.py
uipath_llm_client/clients/openai/utils.py
uipath_llm_client/settings/__init__.py
uipath_llm_client/settings/base.py
uipath_llm_client/settings/utils.py
uipath_llm_client/settings/agenthub/__init__.py
uipath_llm_client/settings/agenthub/auth.py
uipath_llm_client/settings/agenthub/settings.py
uipath_llm_client/settings/agenthub/utils.py
uipath_llm_client/settings/llmgateway/__init__.py
uipath_llm_client/settings/llmgateway/auth.py
uipath_llm_client/settings/llmgateway/settings.py
uipath_llm_client/settings/llmgateway/utils.py
uipath_llm_client/utils/exceptions.py
uipath_llm_client/utils/logging.py
uipath_llm_client/utils/retry.py
uipath_llm_client-1.0.1.dist-info/METADATA
uipath_llm_client-1.0.1.dist-info/WHEEL
uipath_llm_client-1.0.1.dist-info/licenses/LICENSE
uipath_llm_client-1.0.1.dist-info/RECORD
