Metadata-Version: 2.4
Name: uipath-llm-client
Version: 1.0.1
Summary: UiPath LLM Client
Author-email: Cosmin Maria <cosmin.maria@uipath.com>, Dragos Bobolea <dragos.bobolea@uipath.com>
License-File: LICENSE
Requires-Python: >=3.11
Requires-Dist: httpx>=0.28.1
Requires-Dist: pydantic-settings>=2.12.0
Requires-Dist: pydantic>=2.12.5
Requires-Dist: tenacity>=9.1.2
Requires-Dist: uipath>=2.5.17
Provides-Extra: all
Requires-Dist: anthropic>=0.76.0; extra == 'all'
Requires-Dist: google-genai>=1.59.0; extra == 'all'
Requires-Dist: openai>=2.15.0; extra == 'all'
Provides-Extra: anthropic
Requires-Dist: anthropic>=0.76.0; extra == 'anthropic'
Provides-Extra: google
Requires-Dist: google-genai>=1.59.0; extra == 'google'
Provides-Extra: openai
Requires-Dist: openai>=2.15.0; extra == 'openai'
